hexrgb/__init__.py
hexrgb/main.py
hexrgb-1.0.0.dist-info/licenses/LICENSE
hexrgb-1.0.0.dist-info/METADATA
hexrgb-1.0.0.dist-info/WHEEL
hexrgb-1.0.0.dist-info/entry_points.txt
hexrgb-1.0.0.dist-info/top_level.txt
hexrgb-1.0.0.dist-info/RECORD
