Metadata-Version: 2.4
Name: hexrgb
Version: 1.0.0
Summary: Convert HEX color code to RGB.
Author: Mallik Mohammad Musaddiq
Author-email: Mallik Mohammad Musaddiq <mallikmusaddiq1@gmail.com>
License: MIT
Requires-Python: >=3.6
License-File: LICENSE
Dynamic: author
Dynamic: license-file
Dynamic: requires-python
